cimem/__init__.py
cimem/core.py
cimem-0.0.0.dist-info/METADATA
cimem-0.0.0.dist-info/RECORD
cimem-0.0.0.dist-info/WHEEL
cimem-0.0.0.dist-info/top_level.txt
